{
  "meta": {
    "store_id": "2065",
    "report_date": "2026-07-21",
    "generated": "2026-07-22T11:27:57",
    "source_pdf": "data/raw/parbrink/2065/2026-07-21/Hourly Sales And Labor.pdf"
  },
  "totals": {
    "net_sales": 3831.1,
    "guests": 745,
    "guest_average": 5.14,
    "orders": 167,
    "order_average": 22.94,
    "labor_hours": 64.65,
    "labor_dollars": 902.39,
    "labor_percent": 23.55,
    "avg_hourly_wage": 13.96
  },
  "hours": [
    {
      "hour_24": 4,
      "label": "4A",
      "net_sales": 0.0,
      "guests": 0,
      "guest_average": 0.0,
      "orders": 0,
      "order_average": 0.0,
      "labor_hours": 0.0,
      "labor_dollars": 0.0,
      "labor_percent": 0.0
    },
    {
      "hour_24": 5,
      "label": "5A",
      "net_sales": 0.0,
      "guests": 0,
      "guest_average": 0.0,
      "orders": 0,
      "order_average": 0.0,
      "labor_hours": 0.0,
      "labor_dollars": 0.0,
      "labor_percent": 0.0
    },
    {
      "hour_24": 6,
      "label": "6A",
      "net_sales": 0.0,
      "guests": 0,
      "guest_average": 0.0,
      "orders": 0,
      "order_average": 0.0,
      "labor_hours": 0.0,
      "labor_dollars": 0.0,
      "labor_percent": 0.0
    },
    {
      "hour_24": 7,
      "label": "7A",
      "net_sales": 0.0,
      "guests": 0,
      "guest_average": 0.0,
      "orders": 0,
      "order_average": 0.0,
      "labor_hours": 0.9,
      "labor_dollars": 15.8,
      "labor_percent": 100.0
    },
    {
      "hour_24": 8,
      "label": "8A",
      "net_sales": 0.0,
      "guests": 0,
      "guest_average": 0.0,
      "orders": 0,
      "order_average": 0.0,
      "labor_hours": 2.03,
      "labor_dollars": 33.37,
      "labor_percent": 100.0
    },
    {
      "hour_24": 9,
      "label": "9A",
      "net_sales": 0.0,
      "guests": 0,
      "guest_average": 0.0,
      "orders": 0,
      "order_average": 0.0,
      "labor_hours": 3.08,
      "labor_dollars": 45.0,
      "labor_percent": 100.0
    },
    {
      "hour_24": 10,
      "label": "10A",
      "net_sales": 0.0,
      "guests": 0,
      "guest_average": 0.0,
      "orders": 0,
      "order_average": 0.0,
      "labor_hours": 3.1,
      "labor_dollars": 43.65,
      "labor_percent": 100.0
    },
    {
      "hour_24": 11,
      "label": "11A",
      "net_sales": 209.0,
      "guests": 36,
      "guest_average": 5.81,
      "orders": 11,
      "order_average": 19.0,
      "labor_hours": 4.0,
      "labor_dollars": 56.0,
      "labor_percent": 26.79
    },
    {
      "hour_24": 12,
      "label": "12P",
      "net_sales": 575.15,
      "guests": 108,
      "guest_average": 5.33,
      "orders": 26,
      "order_average": 22.12,
      "labor_hours": 4.0,
      "labor_dollars": 56.0,
      "labor_percent": 9.74
    },
    {
      "hour_24": 13,
      "label": "1P",
      "net_sales": 156.2,
      "guests": 47,
      "guest_average": 3.32,
      "orders": 14,
      "order_average": 11.16,
      "labor_hours": 3.72,
      "labor_dollars": 52.6,
      "labor_percent": 33.67
    },
    {
      "hour_24": 14,
      "label": "2P",
      "net_sales": 238.81,
      "guests": 45,
      "guest_average": 5.31,
      "orders": 9,
      "order_average": 26.53,
      "labor_hours": 3.87,
      "labor_dollars": 54.6,
      "labor_percent": 22.86
    },
    {
      "hour_24": 15,
      "label": "3P",
      "net_sales": 149.17,
      "guests": 31,
      "guest_average": 4.81,
      "orders": 8,
      "order_average": 18.65,
      "labor_hours": 3.02,
      "labor_dollars": 40.53,
      "labor_percent": 27.17
    },
    {
      "hour_24": 16,
      "label": "4P",
      "net_sales": 366.07,
      "guests": 68,
      "guest_average": 5.38,
      "orders": 15,
      "order_average": 24.4,
      "labor_hours": 3.02,
      "labor_dollars": 42.28,
      "labor_percent": 11.55
    },
    {
      "hour_24": 17,
      "label": "5P",
      "net_sales": 431.04,
      "guests": 86,
      "guest_average": 5.01,
      "orders": 16,
      "order_average": 26.94,
      "labor_hours": 4.85,
      "labor_dollars": 67.85,
      "labor_percent": 15.74
    },
    {
      "hour_24": 18,
      "label": "6P",
      "net_sales": 531.21,
      "guests": 102,
      "guest_average": 5.21,
      "orders": 22,
      "order_average": 24.15,
      "labor_hours": 5.93,
      "labor_dollars": 80.36,
      "labor_percent": 15.13
    },
    {
      "hour_24": 19,
      "label": "7P",
      "net_sales": 644.61,
      "guests": 121,
      "guest_average": 5.33,
      "orders": 20,
      "order_average": 32.23,
      "labor_hours": 5.1,
      "labor_dollars": 66.6,
      "labor_percent": 10.33
    },
    {
      "hour_24": 20,
      "label": "8P",
      "net_sales": 374.78,
      "guests": 68,
      "guest_average": 5.51,
      "orders": 15,
      "order_average": 24.99,
      "labor_hours": 5.27,
      "labor_dollars": 73.18,
      "labor_percent": 19.53
    },
    {
      "hour_24": 21,
      "label": "9P",
      "net_sales": 155.06,
      "guests": 33,
      "guest_average": 4.7,
      "orders": 11,
      "order_average": 14.1,
      "labor_hours": 5.57,
      "labor_dollars": 76.48,
      "labor_percent": 49.32
    },
    {
      "hour_24": 22,
      "label": "10P",
      "net_sales": 0.0,
      "guests": 0,
      "guest_average": 0.0,
      "orders": 0,
      "order_average": 0.0,
      "labor_hours": 6.0,
      "labor_dollars": 81.25,
      "labor_percent": 100.0
    },
    {
      "hour_24": 23,
      "label": "11P",
      "net_sales": 0.0,
      "guests": 0,
      "guest_average": 0.0,
      "orders": 0,
      "order_average": 0.0,
      "labor_hours": 1.2,
      "labor_dollars": 16.84,
      "labor_percent": 100.0
    },
    {
      "hour_24": 0,
      "label": "12A",
      "net_sales": 0.0,
      "guests": 0,
      "guest_average": 0.0,
      "orders": 0,
      "order_average": 0.0,
      "labor_hours": 0.0,
      "labor_dollars": 0.0,
      "labor_percent": 0.0
    },
    {
      "hour_24": 1,
      "label": "1A",
      "net_sales": 0.0,
      "guests": 0,
      "guest_average": 0.0,
      "orders": 0,
      "order_average": 0.0,
      "labor_hours": 0.0,
      "labor_dollars": 0.0,
      "labor_percent": 0.0
    },
    {
      "hour_24": 2,
      "label": "2A",
      "net_sales": 0.0,
      "guests": 0,
      "guest_average": 0.0,
      "orders": 0,
      "order_average": 0.0,
      "labor_hours": 0.0,
      "labor_dollars": 0.0,
      "labor_percent": 0.0
    },
    {
      "hour_24": 3,
      "label": "3A",
      "net_sales": 0.0,
      "guests": 0,
      "guest_average": 0.0,
      "orders": 0,
      "order_average": 0.0,
      "labor_hours": 0.0,
      "labor_dollars": 0.0,
      "labor_percent": 0.0
    }
  ]
}