{
  "meta": {
    "report_date": "2026-06-15",
    "report_display": "Monday, June 15, 2026",
    "generated": "6/16/2026 at 10:33 AM"
  },
  "sales": {
    "net": 4161.0,
    "net_week": 4161.0,
    "ly": 2979.0,
    "ly_week": 2979.0,
    "forecast": 4476.0,
    "forecast_week": 4476.0,
    "vs_ly": 1182.0,
    "vs_ly_week": 1182.0,
    "vs_forecast": -315.0,
    "per_guest": 5.27,
    "per_guest_week": 5.27
  },
  "labor": {
    "cost": 15.0,
    "cost_week": 15.0,
    "pct": 20.84,
    "pct_week": 20.84,
    "actual_hours": 0.0,
    "actual_hours_week": 0.0,
    "sched_hours": 80.25,
    "sched_hours_week": 80.25,
    "hours_variance": null,
    "productivity": 56.0,
    "productivity_week": 56.0,
    "hours_var": null
  },
  "cash": {
    "over_short": 0.0
  },
  "comps": [
    {
      "name": "Comps and Discounts",
      "day": "$61.52",
      "week": "$61.52"
    }
  ],
  "raw": {
    "Actual Net Sales": {
      "day": "$4,161",
      "week": "$4,161"
    },
    "Last Year Same Day": {
      "day": "$2,979",
      "week": "$2,979"
    },
    "Forecasted Sales": {
      "day": "$4,476",
      "week": "$4,476"
    },
    "Net Sales to Last Year": {
      "day": "$1,182",
      "week": "$1,182"
    },
    "Actual Labor": {
      "day": "15",
      "week": "15"
    },
    "Hours Variance": {
      "day": "",
      "week": ""
    },
    "Labor % of Net Sales": {
      "day": "20.84%",
      "week": "20.84%"
    },
    "Total Cash Over/Short": {
      "day": "$0.00",
      "week": "$0.00"
    },
    "Comps and Discounts": {
      "day": "$61.52",
      "week": "$61.52"
    },
    "Sales / Guest": {
      "day": "$5.27",
      "week": "$5.27"
    },
    "Labor Productivity": {
      "day": "$56",
      "week": "$56"
    },
    "Actual Hours": {
      "day": "0.00",
      "week": "0.00"
    },
    "Scheduled Hours": {
      "day": "80.25",
      "week": "80.25"
    }
  }
}