{
  "meta": {
    "store_id": "2065",
    "anchor_date": "2026-05-05",
    "generated": "2026-05-06T08:08:35",
    "days_seen_total": 11,
    "days_in_week": 7,
    "days_in_month": 11,
    "days_in_quarter": 11
  },
  "week": {
    "net_sales": 31737.59,
    "gross_sales": 33016.46,
    "order_count": 1275,
    "guest_count": 5955,
    "labor_cost": 6541.62,
    "labor_hours": 531.89,
    "labor_percent": 20.61,
    "sales_per_guest": 5.33,
    "avg_ticket": 24.89,
    "days": 7
  },
  "month": {
    "net_sales": 50346.66,
    "gross_sales": 51943.07,
    "order_count": 2001,
    "guest_count": 9352,
    "labor_cost": 10244.35,
    "labor_hours": 834.87,
    "labor_percent": 20.35,
    "sales_per_guest": 5.38,
    "avg_ticket": 25.16,
    "days": 11
  },
  "quarter": {
    "net_sales": 50346.66,
    "gross_sales": 51943.07,
    "order_count": 2001,
    "guest_count": 9352,
    "labor_cost": 10244.35,
    "labor_hours": 834.87,
    "labor_percent": 20.35,
    "sales_per_guest": 5.38,
    "avg_ticket": 25.16,
    "days": 11
  }
}