{
  "meta": {
    "store_id": "2065",
    "report_date": "2026-06-09",
    "generated": "2026-06-10T12:46:19",
    "source_pdf": "data/raw/parbrink/2065/2026-06-09/Hourly Sales And Labor.pdf"
  },
  "totals": {
    "net_sales": 3350.04,
    "guests": 629,
    "guest_average": 5.33,
    "orders": 159,
    "order_average": 21.07,
    "labor_hours": 64.27,
    "labor_dollars": 855.66,
    "labor_percent": 25.54,
    "avg_hourly_wage": 13.31
  },
  "hours": [
    {
      "hour_24": 4,
      "label": "4A",
      "net_sales": 0.0,
      "guests": 0,
      "guest_average": 0.0,
      "orders": 0,
      "order_average": 0.0,
      "labor_hours": 0.0,
      "labor_dollars": 0.0,
      "labor_percent": 0.0
    },
    {
      "hour_24": 5,
      "label": "5A",
      "net_sales": 0.0,
      "guests": 0,
      "guest_average": 0.0,
      "orders": 0,
      "order_average": 0.0,
      "labor_hours": 0.0,
      "labor_dollars": 0.0,
      "labor_percent": 0.0
    },
    {
      "hour_24": 6,
      "label": "6A",
      "net_sales": 0.0,
      "guests": 0,
      "guest_average": 0.0,
      "orders": 0,
      "order_average": 0.0,
      "labor_hours": 0.0,
      "labor_dollars": 0.0,
      "labor_percent": 0.0
    },
    {
      "hour_24": 7,
      "label": "7A",
      "net_sales": 0.0,
      "guests": 0,
      "guest_average": 0.0,
      "orders": 0,
      "order_average": 0.0,
      "labor_hours": 0.0,
      "labor_dollars": 0.0,
      "labor_percent": 0.0
    },
    {
      "hour_24": 8,
      "label": "8A",
      "net_sales": 0.0,
      "guests": 0,
      "guest_average": 0.0,
      "orders": 0,
      "order_average": 0.0,
      "labor_hours": 2.07,
      "labor_dollars": 31.73,
      "labor_percent": 100.0
    },
    {
      "hour_24": 9,
      "label": "9A",
      "net_sales": 0.0,
      "guests": 0,
      "guest_average": 0.0,
      "orders": 0,
      "order_average": 0.0,
      "labor_hours": 3.17,
      "labor_dollars": 43.96,
      "labor_percent": 100.0
    },
    {
      "hour_24": 10,
      "label": "10A",
      "net_sales": 0.0,
      "guests": 0,
      "guest_average": 0.0,
      "orders": 0,
      "order_average": 0.0,
      "labor_hours": 2.95,
      "labor_dollars": 38.65,
      "labor_percent": 100.0
    },
    {
      "hour_24": 11,
      "label": "11A",
      "net_sales": 279.97,
      "guests": 53,
      "guest_average": 5.28,
      "orders": 14,
      "order_average": 20.0,
      "labor_hours": 4.0,
      "labor_dollars": 53.75,
      "labor_percent": 19.2
    },
    {
      "hour_24": 12,
      "label": "12P",
      "net_sales": 410.17,
      "guests": 83,
      "guest_average": 4.94,
      "orders": 25,
      "order_average": 16.41,
      "labor_hours": 4.0,
      "labor_dollars": 53.75,
      "labor_percent": 13.1
    },
    {
      "hour_24": 13,
      "label": "1P",
      "net_sales": 342.7,
      "guests": 62,
      "guest_average": 5.53,
      "orders": 17,
      "order_average": 20.16,
      "labor_hours": 3.92,
      "labor_dollars": 52.42,
      "labor_percent": 15.3
    },
    {
      "hour_24": 14,
      "label": "2P",
      "net_sales": 284.99,
      "guests": 52,
      "guest_average": 5.48,
      "orders": 14,
      "order_average": 20.36,
      "labor_hours": 3.6,
      "labor_dollars": 45.85,
      "labor_percent": 16.09
    },
    {
      "hour_24": 15,
      "label": "3P",
      "net_sales": 147.14,
      "guests": 29,
      "guest_average": 5.07,
      "orders": 7,
      "order_average": 21.02,
      "labor_hours": 5.52,
      "labor_dollars": 71.7,
      "labor_percent": 48.73
    },
    {
      "hour_24": 16,
      "label": "4P",
      "net_sales": 273.78,
      "guests": 53,
      "guest_average": 5.17,
      "orders": 14,
      "order_average": 19.56,
      "labor_hours": 4.9,
      "labor_dollars": 63.58,
      "labor_percent": 23.22
    },
    {
      "hour_24": 17,
      "label": "5P",
      "net_sales": 400.52,
      "guests": 73,
      "guest_average": 5.49,
      "orders": 17,
      "order_average": 23.56,
      "labor_hours": 5.52,
      "labor_dollars": 72.93,
      "labor_percent": 18.21
    },
    {
      "hour_24": 18,
      "label": "6P",
      "net_sales": 419.04,
      "guests": 73,
      "guest_average": 5.74,
      "orders": 14,
      "order_average": 29.93,
      "labor_hours": 6.0,
      "labor_dollars": 78.25,
      "labor_percent": 18.67
    },
    {
      "hour_24": 19,
      "label": "7P",
      "net_sales": 394.48,
      "guests": 78,
      "guest_average": 5.06,
      "orders": 17,
      "order_average": 23.2,
      "labor_hours": 4.55,
      "labor_dollars": 61.59,
      "labor_percent": 15.61
    },
    {
      "hour_24": 20,
      "label": "8P",
      "net_sales": 282.74,
      "guests": 53,
      "guest_average": 5.33,
      "orders": 15,
      "order_average": 18.85,
      "labor_hours": 5.0,
      "labor_dollars": 66.5,
      "labor_percent": 23.52
    },
    {
      "hour_24": 21,
      "label": "9P",
      "net_sales": 114.51,
      "guests": 20,
      "guest_average": 5.73,
      "orders": 5,
      "order_average": 22.9,
      "labor_hours": 5.0,
      "labor_dollars": 66.5,
      "labor_percent": 58.07
    },
    {
      "hour_24": 22,
      "label": "10P",
      "net_sales": 0.0,
      "guests": 0,
      "guest_average": 0.0,
      "orders": 0,
      "order_average": 0.0,
      "labor_hours": 4.08,
      "labor_dollars": 54.5,
      "labor_percent": 100.0
    },
    {
      "hour_24": 23,
      "label": "11P",
      "net_sales": 0.0,
      "guests": 0,
      "guest_average": 0.0,
      "orders": 0,
      "order_average": 0.0,
      "labor_hours": 0.0,
      "labor_dollars": 0.0,
      "labor_percent": 0.0
    },
    {
      "hour_24": 0,
      "label": "12A",
      "net_sales": 0.0,
      "guests": 0,
      "guest_average": 0.0,
      "orders": 0,
      "order_average": 0.0,
      "labor_hours": 0.0,
      "labor_dollars": 0.0,
      "labor_percent": 0.0
    },
    {
      "hour_24": 1,
      "label": "1A",
      "net_sales": 0.0,
      "guests": 0,
      "guest_average": 0.0,
      "orders": 0,
      "order_average": 0.0,
      "labor_hours": 0.0,
      "labor_dollars": 0.0,
      "labor_percent": 0.0
    },
    {
      "hour_24": 2,
      "label": "2A",
      "net_sales": 0.0,
      "guests": 0,
      "guest_average": 0.0,
      "orders": 0,
      "order_average": 0.0,
      "labor_hours": 0.0,
      "labor_dollars": 0.0,
      "labor_percent": 0.0
    },
    {
      "hour_24": 3,
      "label": "3A",
      "net_sales": 0.0,
      "guests": 0,
      "guest_average": 0.0,
      "orders": 0,
      "order_average": 0.0,
      "labor_hours": 0.0,
      "labor_dollars": 0.0,
      "labor_percent": 0.0
    }
  ]
}