{
  "date": "2026-04-18",
  "store": "2065",
  "rows": [
    {
      "hour": "4:00\u00c2\u00a0AM",
      "netSales": 0,
      "guests": 0,
      "orders": 0,
      "laborHrs": 0,
      "laborDollars": 0,
      "laborPct": 0
    },
    {
      "hour": "5:00\u00c2\u00a0AM",
      "netSales": 0,
      "guests": 0,
      "orders": 0,
      "laborHrs": 0,
      "laborDollars": 0,
      "laborPct": 0
    },
    {
      "hour": "6:00\u00c2\u00a0AM",
      "netSales": 0,
      "guests": 0,
      "orders": 0,
      "laborHrs": 0.67,
      "laborDollars": 12,
      "laborPct": 100
    },
    {
      "hour": "7:00\u00c2\u00a0AM",
      "netSales": 0,
      "guests": 0,
      "orders": 0,
      "laborHrs": 1.25,
      "laborDollars": 21.3,
      "laborPct": 100
    },
    {
      "hour": "8:00\u00c2\u00a0AM",
      "netSales": 0,
      "guests": 0,
      "orders": 0,
      "laborHrs": 4,
      "laborDollars": 57,
      "laborPct": 100
    },
    {
      "hour": "9:00\u00c2\u00a0AM",
      "netSales": 0,
      "guests": 0,
      "orders": 0,
      "laborHrs": 4,
      "laborDollars": 57,
      "laborPct": 100
    },
    {
      "hour": "10:00\u00c2\u00a0AM",
      "netSales": 25.45,
      "guests": 5,
      "orders": 1,
      "laborHrs": 2.73,
      "laborDollars": 38.95,
      "laborPct": 153.05
    },
    {
      "hour": "11:00\u00c2\u00a0AM",
      "netSales": 345.63,
      "guests": 55,
      "orders": 12,
      "laborHrs": 4.9,
      "laborDollars": 48.9,
      "laborPct": 14.15
    },
    {
      "hour": "12:00\u00c2\u00a0PM",
      "netSales": 374.11,
      "guests": 64,
      "orders": 13,
      "laborHrs": 5,
      "laborDollars": 50,
      "laborPct": 13.37
    },
    {
      "hour": "1:00\u00c2\u00a0PM",
      "netSales": 210.81,
      "guests": 38,
      "orders": 7,
      "laborHrs": 5,
      "laborDollars": 50,
      "laborPct": 23.72
    },
    {
      "hour": "2:00\u00c2\u00a0PM",
      "netSales": 404.8,
      "guests": 76,
      "orders": 21,
      "laborHrs": 3.63,
      "laborDollars": 34.32,
      "laborPct": 8.48
    },
    {
      "hour": "3:00\u00c2\u00a0PM",
      "netSales": 473.27,
      "guests": 85,
      "orders": 17,
      "laborHrs": 5.5,
      "laborDollars": 54.51,
      "laborPct": 11.52
    },
    {
      "hour": "4:00\u00c2\u00a0PM",
      "netSales": 458.07,
      "guests": 83,
      "orders": 19,
      "laborHrs": 4.17,
      "laborDollars": 35.87,
      "laborPct": 7.83
    },
    {
      "hour": "5:00\u00c2\u00a0PM",
      "netSales": 310.21,
      "guests": 59,
      "orders": 14,
      "laborHrs": 4.23,
      "laborDollars": 36.43,
      "laborPct": 11.74
    },
    {
      "hour": "6:00\u00c2\u00a0PM",
      "netSales": 464.98,
      "guests": 85,
      "orders": 19,
      "laborHrs": 4.6,
      "laborDollars": 40.85,
      "laborPct": 8.79
    },
    {
      "hour": "7:00\u00c2\u00a0PM",
      "netSales": 622.66,
      "guests": 121,
      "orders": 21,
      "laborHrs": 5.87,
      "laborDollars": 49.74,
      "laborPct": 7.99
    },
    {
      "hour": "8:00\u00c2\u00a0PM",
      "netSales": 543.39,
      "guests": 99,
      "orders": 19,
      "laborHrs": 7.68,
      "laborDollars": 64.6,
      "laborPct": 11.89
    },
    {
      "hour": "9:00\u00c2\u00a0PM",
      "netSales": 100.29,
      "guests": 20,
      "orders": 5,
      "laborHrs": 8,
      "laborDollars": 68.25,
      "laborPct": 68.05
    },
    {
      "hour": "10:00\u00c2\u00a0PM",
      "netSales": 0,
      "guests": 0,
      "orders": 0,
      "laborHrs": 7.07,
      "laborDollars": 57.68,
      "laborPct": 100
    },
    {
      "hour": "11:00\u00c2\u00a0PM",
      "netSales": 0,
      "guests": 0,
      "orders": 0,
      "laborHrs": 2,
      "laborDollars": 0,
      "laborPct": 0
    },
    {
      "hour": "12:00\u00c2\u00a0AM",
      "netSales": 0,
      "guests": 0,
      "orders": 0,
      "laborHrs": 2,
      "laborDollars": 0,
      "laborPct": 0
    },
    {
      "hour": "1:00\u00c2\u00a0AM",
      "netSales": 0,
      "guests": 0,
      "orders": 0,
      "laborHrs": 2,
      "laborDollars": 0,
      "laborPct": 0
    },
    {
      "hour": "2:00\u00c2\u00a0AM",
      "netSales": 0,
      "guests": 0,
      "orders": 0,
      "laborHrs": 2,
      "laborDollars": 0,
      "laborPct": 0
    },
    {
      "hour": "3:00\u00c2\u00a0AM",
      "netSales": 0,
      "guests": 0,
      "orders": 0,
      "laborHrs": 2,
      "laborDollars": 0,
      "laborPct": 0
    }
  ],
  "_source": "Chrome MCP localStorage dump"
}